py_machine/__init__.py
py_machine/base74.py
py_machine/cell.py
py_machine/code_to_level.py
py_machine/level.py
py_machine/placeable.py
py_machine_The_Hexagon-0.0.3.dist-info/LICENCE
py_machine_The_Hexagon-0.0.3.dist-info/METADATA
py_machine_The_Hexagon-0.0.3.dist-info/WHEEL
py_machine_The_Hexagon-0.0.3.dist-info/top_level.txt
py_machine_The_Hexagon-0.0.3.dist-info/RECORD
