Metadata-Version: 2.1
Name: py-machine-The-Hexagon
Version: 0.0.3
Summary: A package for creating levels in cell machine mystic mod
Home-page: https://github.com/The-Decent-Hexagon/py_machine
Author: Hex
Author-email: hexsmoth@gmail.com
License: UNKNOWN
Project-URL: Bug Tracker, https://github.com/The-Decent-Hexagon/py_machine/issues
Platform: UNKNOWN
Classifier: Programming Language :: Python :: 3
Classifier: License :: OSI Approved :: MIT License
Classifier: Operating System :: OS Independent
Requires-Python: >=3.6
License-File: LICENCE
